{
  "earningsIncludedUpTo": "2015-04-05",
  "amounts": {
    "protectedPayment": false,
    "current": {
      "weeklyAmount": 123.07,
      "monthlyAmount": 535.13,
      "annualAmount": 6421.62
    },
    "forecast": {
      "yearsToWork": 8,
      "weeklyAmount": 155.65,
      "monthlyAmount": 676.8,
      "annualAmount": 8121.59
    },
    "maximum": {
      "yearsToWork": 8,
      "gapsToFill": 0,
      "weeklyAmount": 155.65,
      "monthlyAmount": 676.8,
      "annualAmount": 8121.59
    },
    "cope": {
      "weeklyAmount": 46.39,
      "monthlyAmount": 201.71,
      "annualAmount": 2420.56
    }
  },
  "pensionAge": 66,
  "pensionDate": "2026-03-14",
  "finalRelevantYear": "2024-25",
  "numberOfQualifyingYears": 35,
  "pensionSharingOrder": false,
  "currentFullWeeklyPensionAmount": 155.65
}